setup.py
ProbPy/__init__.py
ProbPy/bn.py
ProbPy/event.py
ProbPy/factor.py
ProbPy/inf_theory.py
ProbPy/mn.py
ProbPy/rand_var.py
ProbPy/tmn.py
ProbPy.egg-info/PKG-INFO
ProbPy.egg-info/SOURCES.txt
ProbPy.egg-info/dependency_links.txt
ProbPy.egg-info/top_level.txt