Metadata-Version: 1.1
Name: ProbPy
Version: 1.0
Summary: Multi Variable Probability Calculus Library
Home-page: https://github.com/petermlm/ProbPy
Author: Pedro Melgueira
Author-email: pedromelgueira@gmail.com
License: MIT License
Keywords: probability calculus random variable bayes bayesian network                information theory markov
Platform: UNKNOWN
Classifier: Development Status :: 4 - Beta
Classifier: Environment :: Console
Classifier: Intended Audience :: Developers
Classifier: Intended Audience :: Education
Classifier: Intended Audience :: End Users/Desktop
Classifier: Intended Audience :: Science/Research
Classifier: License :: OSI Approved :: MIT License
Classifier: Natural Language :: English
Classifier: Operating System :: POSIX :: Linux
Classifier: Programming Language :: Python :: 3
Classifier: Topic :: Scientific/Engineering
Classifier: Topic :: Software Development :: Libraries
